{
  "type": "object",
  "$schema": "https://json-structure.org/meta/core/v0/#",
  "$id": "https://raw.githubusercontent.com/api-evangelist/apache-james/refs/heads/main/json-structure/webadmin-rest-api-health-check-result-structure.json",
  "name": "HealthCheckResult",
  "description": "Health check results for all components",
  "properties": {
    "status": {
      "type": "string",
      "description": "Overall health status",
      "enum": [
        "healthy",
        "degraded",
        "unhealthy"
      ],
      "example": "healthy"
    },
    "checks": {
      "type": "array",
      "description": "Individual component checks",
      "items": {
        "$ref": "#/components/schemas/ComponentCheck"
      }
    }
  }
}